resource_locker/__init__.py
resource_locker/_version.py
resource_locker/__pycache__/__init__.cpython-36.pyc
resource_locker/__pycache__/_version.cpython-36.pyc
resource_locker/core/__init__.py
resource_locker/core/exceptions.py
resource_locker/core/lock.py
resource_locker/core/potential.py
resource_locker/core/requirement.py
resource_locker/core/__pycache__/__init__.cpython-36.pyc
resource_locker/core/__pycache__/exceptions.cpython-36.pyc
resource_locker/core/__pycache__/lock.cpython-36.pyc
resource_locker/core/__pycache__/potential.cpython-36.pyc
resource_locker/core/__pycache__/requirement.cpython-36.pyc
resource_locker/factories/__init__.py
resource_locker/factories/meta.py
resource_locker/factories/native.py
resource_locker/factories/redis.py
resource_locker/factories/__pycache__/__init__.cpython-36.pyc
resource_locker/factories/__pycache__/meta.cpython-36.pyc
resource_locker/factories/__pycache__/native.cpython-36.pyc
resource_locker/factories/__pycache__/redis.cpython-36.pyc
resource_locker/reporter/__init__.py
resource_locker/reporter/aspects.py
resource_locker/reporter/query.py
resource_locker/reporter/reporter.py
resource_locker/reporter/timer.py
resource_locker/reporter/__pycache__/__init__.cpython-36.pyc
resource_locker/reporter/__pycache__/aspects.cpython-36.pyc
resource_locker/reporter/__pycache__/query.cpython-36.pyc
resource_locker/reporter/__pycache__/reporter.cpython-36.pyc
resource_locker/reporter/__pycache__/timer.cpython-36.pyc
resource_locker-1.0.0.dist-info/DESCRIPTION.rst
resource_locker-1.0.0.dist-info/METADATA
resource_locker-1.0.0.dist-info/RECORD
resource_locker-1.0.0.dist-info/WHEEL
resource_locker-1.0.0.dist-info/metadata.json
resource_locker-1.0.0.dist-info/top_level.txt
