Metadata-Version: 2.0
Name: resource-locker
Version: 1.0.0
Summary: Local resource allocation with shared/distributed locks
Home-page: https://github.com/ARMmbed/resource_locker
License: Apache 2.0
Platform: UNKNOWN
Classifier: Intended Audience :: Developers
Requires-Python: >3.4
Requires-Dist: redlock
Requires-Dist: python-redis-lock
Requires-Dist: redis
Requires-Dist: retrying
